ggshots/__init__.py
ggshots/ggshots.py
ggshots-0.3.0.dist-info/DESCRIPTION.rst
ggshots-0.3.0.dist-info/METADATA
ggshots-0.3.0.dist-info/RECORD
ggshots-0.3.0.dist-info/WHEEL
ggshots-0.3.0.dist-info/entry_points.txt
ggshots-0.3.0.dist-info/metadata.json
ggshots-0.3.0.dist-info/top_level.txt
