Metadata-Version: 2.0
Name: ggshots
Version: 0.3.0
Summary: A utility to generate screenshots of google search results
Home-page: https://github.com/YBadiss/ggshotsproject
Author: Yacine Badiss
Author-email: yacine.badiss@gmail.com
License: MIT
Keywords: screenshot google search
Platform: UNKNOWN
Classifier: Development Status :: 3 - Alpha
Classifier: Intended Audience :: Developers
Classifier: License :: OSI Approved :: MIT License
Classifier: Programming Language :: Python :: 2.7
Requires-Dist: click
Requires-Dist: python-docx
Requires-Dist: webkit2png
